{"legislative_session": "2025", "identifier": "SB 43", "title": "Modifies provisions relating to protection of vulnerable persons", "from_organization": "~{\"classification\": \"upper\"}", "classification": ["bill"], "subject": [], "abstracts": [{"note": "abstract", "abstract": "Modifies provisions relating to protection of vulnerable persons"}], "other_titles": [{"note": "", "title": "HCS SS SB 43"}], "other_identifiers": [], "actions": [{"description": "Prefiled", "date": "2024-12-01T06:00:00+00:00", "organization_id": "~{\"classification\": \"upper\"}", "classification": [], "related_entities": []}, {"description": "S First Read", "date": "2025-01-08T06:00:00+00:00", "organization_id": "~{\"classification\": \"upper\"}", "classification": ["reading-1"], "related_entities": []}, {"description": "Second Read and Referred S Families, Seniors and Health Committee", "date": "2025-01-16T06:00:00+00:00", "organization_id": "~{\"classification\": \"upper\"}", "classification": ["reading-2", "referral-committee"], "related_entities": []}, {"description": "Hearing Conducted S Families, Seniors and Health Committee", "date": "2025-01-29T06:00:00+00:00", "organization_id": "~{\"classification\": \"upper\"}", "classification": [], "related_entities": []}, {"description": "Voted Do Pass S Families, Seniors and Health Committee", "date": "2025-02-13T06:00:00+00:00", "organization_id": "~{\"classification\": \"upper\"}", "classification": ["committee-passage"], "related_entities": []}, {"description": "Reported from S Families, Seniors and Health Committee", "date": "2025-02-24T06:00:00+00:00", "organization_id": "~{\"classification\": \"upper\"}", "classification": [], "related_entities": []}, {"description": "SS S offered (Fitzwater)--(1205S.05F)", "date": "2025-03-03T06:00:00+00:00", "organization_id": "~{\"classification\": \"upper\"}", "classification": [], "related_entities": []}, {"description": "SA 1 to SS S offered (Hudson)--(1205S05.02S)", "date": "2025-03-03T06:00:00+00:00", "organization_id": "~{\"classification\": \"upper\"}", "classification": [], "related_entities": []}, {"description": "SA 1 to SA 1 to SS S offered & withdrawn (McCreery)--(1205S05.10S)", "date": "2025-03-03T06:00:00+00:00", "organization_id": "~{\"classification\": \"upper\"}", "classification": [], "related_entities": []}, {"description": "SA 1 to SS S adopted", "date": "2025-03-03T06:00:00+00:00", "organization_id": "~{\"classification\": \"upper\"}", "classification": ["passage"], "related_entities": []}, {"description": "SA 2 to SS S offered & adopted (Brattin)--(1205S05.07S)", "date": "2025-03-03T06:00:00+00:00", "organization_id": "~{\"classification\": \"upper\"}", "classification": [], "related_entities": []}, {"description": "SA 3 to SS S offered & adopted (Moon)--(1205S05.08S)", "date": "2025-03-03T06:00:00+00:00", "organization_id": "~{\"classification\": \"upper\"}", "classification": [], "related_entities": []}, {"description": "SA 4 to SS S offered (Webber)--(1205S05.03S)", "date": "2025-03-03T06:00:00+00:00", "organization_id": "~{\"classification\": \"upper\"}", "classification": [], "related_entities": []}, {"description": "Bill Placed on Informal Calendar", "date": "2025-03-03T06:00:00+00:00", "organization_id": "~{\"classification\": \"upper\"}", "classification": [], "related_entities": []}, {"description": "SA 4 to SS S withdrawn", "date": "2025-03-04T06:00:00+00:00", "organization_id": "~{\"classification\": \"upper\"}", "classification": [], "related_entities": []}, {"description": "SA 5 to SS S offered & adopted (Roberts)--(1205S05.14S)", "date": "2025-03-04T06:00:00+00:00", "organization_id": "~{\"classification\": \"upper\"}", "classification": [], "related_entities": []}, {"description": "SA 6 to SS offered & adopted (McCreery)--(1205S05.01S)", "date": "2025-03-04T06:00:00+00:00", "organization_id": "~{\"classification\": \"upper\"}", "classification": [], "related_entities": []}, {"description": "SA 7 to SS S offered (Brattin)--(1205S05.04S)", "date": "2025-03-04T06:00:00+00:00", "organization_id": "~{\"classification\": \"upper\"}", "classification": [], "related_entities": []}, {"description": "SA 1 to SA 7 to SS S offered & adopted (Nurrenbern)--(1205S05.19S)", "date": "2025-03-04T06:00:00+00:00", "organization_id": "~{\"classification\": \"upper\"}", "classification": [], "related_entities": []}, {"description": "SA 7 to SS, as amended, S adopted", "date": "2025-03-04T06:00:00+00:00", "organization_id": "~{\"classification\": \"upper\"}", "classification": ["passage"], "related_entities": []}, {"description": "SA 8 to SS S offered (Washington)--(1205S05.16S)", "date": "2025-03-04T06:00:00+00:00", "organization_id": "~{\"classification\": \"upper\"}", "classification": [], "related_entities": []}, {"description": "SA 1 to SA 8 to SS S offered & adopted (Coleman)--(1205S05.22S)", "date": "2025-03-04T06:00:00+00:00", "organization_id": "~{\"classification\": \"upper\"}", "classification": [], "related_entities": []}, {"description": "SA 8 to SS, as amended, S adopted", "date": "2025-03-04T06:00:00+00:00", "organization_id": "~{\"classification\": \"upper\"}", "classification": ["passage"], "related_entities": []}, {"description": "SA 9 to SS S offered & adopted (Fitzwater)--(1205S05.23S)", "date": "2025-03-04T06:00:00+00:00", "organization_id": "~{\"classification\": \"upper\"}", "classification": [], "related_entities": []}, {"description": "SA 10 to SS S offered & adopted (Carter)--(1205S05.24S)", "date": "2025-03-04T06:00:00+00:00", "organization_id": "~{\"classification\": \"upper\"}", "classification": [], "related_entities": []}, {"description": "SS, as amended, S adopted", "date": "2025-03-04T06:00:00+00:00", "organization_id": "~{\"classification\": \"upper\"}", "classification": ["passage"], "related_entities": []}, {"description": "Perfected", "date": "2025-03-04T06:00:00+00:00", "organization_id": "~{\"classification\": \"upper\"}", "classification": [], "related_entities": []}, {"description": "Reported Truly Perfected S Rules, Joint Rules, Resolutions and Ethics Committee", "date": "2025-03-04T06:00:00+00:00", "organization_id": "~{\"classification\": \"upper\"}", "classification": [], "related_entities": []}, {"description": "Referred S Fiscal Oversight Committee", "date": "2025-03-04T06:00:00+00:00", "organization_id": "~{\"classification\": \"upper\"}", "classification": ["referral-committee"], "related_entities": []}, {"description": "Voted Do Pass S Fiscal Oversight Committee", "date": "2025-03-06T06:00:00+00:00", "organization_id": "~{\"classification\": \"upper\"}", "classification": ["committee-passage"], "related_entities": []}, {"description": "Reported from S Fiscal Oversight Committee", "date": "2025-03-06T06:00:00+00:00", "organization_id": "~{\"classification\": \"upper\"}", "classification": [], "related_entities": []}, {"description": "S Third Read and Passed", "date": "2025-03-06T06:00:00+00:00", "organization_id": "~{\"classification\": \"upper\"}", "classification": ["passage", "reading-3"], "related_entities": []}, {"description": "H First Read", "date": "2025-03-06T06:00:00+00:00", "organization_id": "~{\"classification\": \"lower\"}", "classification": ["reading-1"], "related_entities": []}, {"description": "H Second Read", "date": "2025-03-10T05:00:00+00:00", "organization_id": "~{\"classification\": \"lower\"}", "classification": ["reading-2"], "related_entities": []}, {"description": "Referred H Judiciary", "date": "2025-03-11T05:00:00+00:00", "organization_id": "~{\"classification\": \"lower\"}", "classification": ["referral-committee"], "related_entities": []}, {"description": "Hearing Conducted H Judiciary", "date": "2025-04-02T05:00:00+00:00", "organization_id": "~{\"classification\": \"lower\"}", "classification": [], "related_entities": []}, {"description": "HCS Voted Do Pass H Judiciary", "date": "2025-04-30T05:00:00+00:00", "organization_id": "~{\"classification\": \"lower\"}", "classification": ["committee-passage"], "related_entities": []}, {"description": "HCS Reported Do Pass H Judiciary", "date": "2025-05-01T05:00:00+00:00", "organization_id": "~{\"classification\": \"lower\"}", "classification": ["committee-passage"], "related_entities": []}, {"description": "Referred H Rules - Legislative", "date": "2025-05-01T05:00:00+00:00", "organization_id": "~{\"classification\": \"lower\"}", "classification": ["referral-committee"], "related_entities": []}, {"description": "HCS Voted Do Pass H Rules - Legislative", "date": "2025-05-06T05:00:00+00:00", "organization_id": "~{\"classification\": \"lower\"}", "classification": ["committee-passage"], "related_entities": []}, {"description": "HCS Reported Do Pass H Rules - Legislative", "date": "2025-05-06T05:00:00+00:00", "organization_id": "~{\"classification\": \"lower\"}", "classification": ["committee-passage"], "related_entities": []}, {"description": "Referred H Fiscal Review Committee", "date": "2025-05-06T05:00:00+00:00", "organization_id": "~{\"classification\": \"lower\"}", "classification": ["referral-committee"], "related_entities": []}, {"description": "HCS Voted Do Pass H Fiscal Review", "date": "2025-05-07T05:00:00+00:00", "organization_id": "~{\"classification\": \"lower\"}", "classification": ["committee-passage"], "related_entities": []}, {"description": "HCS Reported Do Pass H Fiscal Review", "date": "2025-05-07T05:00:00+00:00", "organization_id": "~{\"classification\": \"lower\"}", "classification": ["committee-passage"], "related_entities": []}, {"description": "HA 1 to HCS H offered & adopted (Hausman)--(1205H06.06H)", "date": "2025-05-08T05:00:00+00:00", "organization_id": "~{\"classification\": \"lower\"}", "classification": [], "related_entities": []}, {"description": "HA 2 to HCS H offered (Hausman)--(1205H06.11H)", "date": "2025-05-08T05:00:00+00:00", "organization_id": "~{\"classification\": \"lower\"}", "classification": [], "related_entities": []}, {"description": "HA 1 to HA 2 to HCS H offered & defeated (Myers)--(1205H06.15H)", "date": "2025-05-08T05:00:00+00:00", "organization_id": "~{\"classification\": \"lower\"}", "classification": [], "related_entities": []}, {"description": "HA 2 to HCS H adopted --(1205H06.11H)", "date": "2025-05-08T05:00:00+00:00", "organization_id": "~{\"classification\": \"lower\"}", "classification": [], "related_entities": []}, {"description": "HCS, as amended, H adopted", "date": "2025-05-08T05:00:00+00:00", "organization_id": "~{\"classification\": \"lower\"}", "classification": [], "related_entities": []}, {"description": "H Third Read and Passed", "date": "2025-05-08T05:00:00+00:00", "organization_id": "~{\"classification\": \"lower\"}", "classification": ["passage", "reading-3"], "related_entities": []}, {"description": "S concurs in HCS, as amended", "date": "2025-05-09T05:00:00+00:00", "organization_id": "~{\"classification\": \"upper\"}", "classification": [], "related_entities": []}, {"description": "S Third Read and Passed", "date": "2025-05-09T05:00:00+00:00", "organization_id": "~{\"classification\": \"upper\"}", "classification": ["passage", "reading-3"], "related_entities": []}, {"description": "Truly Agreed To and Finally Passed", "date": "2025-05-09T05:00:00+00:00", "organization_id": "~{\"classification\": \"upper\"}", "classification": ["passage"], "related_entities": []}, {"description": "Signed by House Speaker", "date": "2025-05-29T05:00:00+00:00", "organization_id": "~{\"classification\": \"lower\"}", "classification": [], "related_entities": []}, {"description": "Reported Duly Enrolled Rules, Joint Rules, Resolutions & Ethics Committee", "date": "2025-05-30T05:00:00+00:00", "organization_id": "~{\"classification\": \"upper\"}", "classification": [], "related_entities": []}, {"description": "Signed by Senate President Pro Tem", "date": "2025-05-30T05:00:00+00:00", "organization_id": "~{\"classification\": \"upper\"}", "classification": [], "related_entities": []}, {"description": "Delivered to Governor", "date": "2025-05-30T05:00:00+00:00", "organization_id": "~{\"classification\": \"executive\"}", "classification": [], "related_entities": []}, {"description": "Signed by Governor", "date": "2025-07-09T05:00:00+00:00", "organization_id": "~{\"classification\": \"executive\"}", "classification": ["executive-signature"], "related_entities": []}], "sponsorships": [{"name": "Fitzwater", "classification": "primary", "entity_type": "person", "primary": true, "person_id": "~{\"chamber\": \"upper\", \"name\": \"Fitzwater\"}", "organization_id": null}], "related_bills": [], "versions": [{"note": "Introduced", "links": [{"url": "https://www.senate.mo.gov/25info/pdf-bill/intro/SB43.pdf", "media_type": "application/pdf"}], "date": "", "classification": ""}, {"note": "Perfected", "links": [{"url": "https://www.senate.mo.gov/25info/pdf-bill/perf/SB43.pdf", "media_type": "application/pdf"}], "date": "", "classification": ""}, {"note": "House Committee Substitute", "links": [{"url": "https://www.senate.mo.gov/25info/pdf-bill/House/HCS-SB/SB0043.pdf", "media_type": "application/pdf"}], "date": "", "classification": ""}, {"note": "Truly Agreed To and Finally Passed", "links": [{"url": "https://www.senate.mo.gov/25info/pdf-bill/tat/SB43.pdf", "media_type": "application/pdf"}], "date": "", "classification": ""}, {"note": "1205S.05F - SS\u00a0Adopted, as amended", "links": [{"url": "http://www.senate.mo.gov/25info/BTS_Web/ShowAmendment.aspx?Id=187", "media_type": "application/pdf"}], "date": "", "classification": "amendment"}, {"note": "1205S05.02S - SA 1 SS\u00a0Adopted", "links": [{"url": "http://www.senate.mo.gov/25info/BTS_Web/ShowAmendment.aspx?Id=189", "media_type": "application/pdf"}], "date": "", "classification": "amendment"}, {"note": "1205S05.07S - SA 2 SS\u00a0Adopted", "links": [{"url": "http://www.senate.mo.gov/25info/BTS_Web/ShowAmendment.aspx?Id=196", "media_type": "application/pdf"}], "date": "", "classification": "amendment"}, {"note": "1205S05.08S - SA 3 SS\u00a0Adopted", "links": [{"url": "http://www.senate.mo.gov/25info/BTS_Web/ShowAmendment.aspx?Id=197", "media_type": "application/pdf"}], "date": "", "classification": "amendment"}, {"note": "1205S05.14S - SA 5 SS\u00a0Adopted", "links": [{"url": "http://www.senate.mo.gov/25info/BTS_Web/ShowAmendment.aspx?Id=200", "media_type": "application/pdf"}], "date": "", "classification": "amendment"}, {"note": "1205S05.01S - SA 6 SS\u00a0Adopted", "links": [{"url": "http://www.senate.mo.gov/25info/BTS_Web/ShowAmendment.aspx?Id=201", "media_type": "application/pdf"}], "date": "", "classification": "amendment"}, {"note": "1205S05.04S - SA 7 SS\u00a0Adopted, as amended", "links": [{"url": "http://www.senate.mo.gov/25info/BTS_Web/ShowAmendment.aspx?Id=202", "media_type": "application/pdf"}], "date": "", "classification": "amendment"}, {"note": "1205S05.19S - SA 1 SA 7 SS\u00a0Adopted", "links": [{"url": "http://www.senate.mo.gov/25info/BTS_Web/ShowAmendment.aspx?Id=205", "media_type": "application/pdf"}], "date": "", "classification": "amendment"}, {"note": "1205S05.16S - SA 8  SS\u00a0Adopted, as amended", "links": [{"url": "http://www.senate.mo.gov/25info/BTS_Web/ShowAmendment.aspx?Id=206", "media_type": "application/pdf"}], "date": "", "classification": "amendment"}, {"note": "1205S05.22S - SA 1 SA 8 SS\u00a0Adopted", "links": [{"url": "http://www.senate.mo.gov/25info/BTS_Web/ShowAmendment.aspx?Id=207", "media_type": "application/pdf"}], "date": "", "classification": "amendment"}, {"note": "1205S05.23S - SA 9  SS\u00a0Adopted", "links": [{"url": "http://www.senate.mo.gov/25info/BTS_Web/ShowAmendment.aspx?Id=210", "media_type": "application/pdf"}], "date": "", "classification": "amendment"}, {"note": "1205S05.24S - SA 10 SS\u00a0Adopted", "links": [{"url": "http://www.senate.mo.gov/25info/BTS_Web/ShowAmendment.aspx?Id=211", "media_type": "application/pdf"}], "date": "", "classification": "amendment"}], "documents": [], "citations": [], "sources": [{"url": "http://www.senate.mo.gov/25info/BTS_Web/Bill.aspx?SessionType=R&BillID=207", "note": ""}, {"url": "https://www.senate.mo.gov/25info/BTS_Web/Actions.aspx?SessionType=R&BillID=207", "note": ""}, {"url": "https://www.senate.mo.gov/25info/BTS_Web/BillText.aspx?SessionType=R&BillID=207", "note": ""}], "extras": {}, "jurisdiction": {"id": "ocd-jurisdiction/country:us/state:mo/government", "name": "Missouri", "classification": "state", "division_id": "ocd-division/country:us/state:mo"}, "scraped_at": "2025-07-28T19:28:32+00:00", "_id": "0b50260a-6be9-11f0-a189-ea4745df1a12"}