{"legislative_session": "2025", "identifier": "HCR 2", "title": "Convenes a joint session to receive a message from the Chief Justice of the Supreme Court of Missouri", "from_organization": "~{\"classification\": \"lower\"}", "classification": ["concurrent resolution"], "subject": ["GENERAL ASSEMBLY"], "abstracts": [], "other_titles": [{"note": "official", "title": "HCR 2"}], "other_identifiers": [], "actions": [{"description": "Offered (H)", "date": "2025-01-08T06:00:00+00:00", "organization_id": "~{\"classification\": \"lower\"}", "classification": ["introduction"], "related_entities": []}, {"description": "Adopted (H)", "date": "2025-01-08T06:00:00+00:00", "organization_id": "~{\"classification\": \"lower\"}", "classification": [], "related_entities": []}, {"description": "Reported to the Senate", "date": "2025-01-08T06:00:00+00:00", "organization_id": "~{\"classification\": \"lower\"}", "classification": [], "related_entities": []}, {"description": "Taken Up", "date": "2025-02-20T06:00:00+00:00", "organization_id": "~{\"classification\": \"lower\"}", "classification": [], "related_entities": []}, {"description": "Senate Adopts (S) - AYES: 32 NOES: 0 PRESENT: 0", "date": "2025-02-20T06:00:00+00:00", "organization_id": "~{\"classification\": \"upper\"}", "classification": [], "related_entities": []}, {"description": "Escort Committee - Senators: Schroer, Brattin, Brown (26), Coleman, Hudson, May, McCreery, Mosley, Williams and Webber.", "date": "2025-02-20T06:00:00+00:00", "organization_id": "~{\"classification\": \"lower\"}", "classification": [], "related_entities": []}, {"description": "Senate Message (S)", "date": "2025-02-20T06:00:00+00:00", "organization_id": "~{\"classification\": \"upper\"}", "classification": [], "related_entities": []}, {"description": "Escort Committee - Representatives Riggs, Parker, Gragg, Peters, Crossley, Hein, Steinhoff, Hinman, Shields, and Young.", "date": "2025-02-25T06:00:00+00:00", "organization_id": "~{\"classification\": \"lower\"}", "classification": [], "related_entities": []}, {"description": "House Message (H)", "date": "2025-02-25T06:00:00+00:00", "organization_id": "~{\"classification\": \"lower\"}", "classification": [], "related_entities": []}, {"description": "Escort Committee - Escort committee change removing Senator Brattin and replacing Senator Nicola", "date": "2025-02-26T06:00:00+00:00", "organization_id": "~{\"classification\": \"lower\"}", "classification": [], "related_entities": []}, {"description": "Senate Message (S)", "date": "2025-02-27T06:00:00+00:00", "organization_id": "~{\"classification\": \"upper\"}", "classification": [], "related_entities": []}], "sponsorships": [{"name": "Alex Riley", "classification": "primary", "entity_type": "person", "primary": true, "person_id": "~{\"name\": \"Alex Riley\"}", "organization_id": null}], "related_bills": [], "versions": [{"note": "Introduced", "links": [{"url": "https://documents.house.mo.gov/billtracking/bills251/hlrbillspdf/1938H.02I.pdf", "media_type": "application/pdf"}], "date": "", "classification": ""}], "documents": [], "citations": [], "sources": [{"url": "https://www.house.mo.gov/BillContent.aspx?bill=HCR2&year=2025&code=R&style=new", "note": ""}, {"url": "https://house.mo.gov/billactions.aspx?bill=HCR2&year=2025&code=R", "note": ""}], "extras": {}, "jurisdiction": {"id": "ocd-jurisdiction/country:us/state:mo/government", "name": "Missouri", "classification": "state", "division_id": "ocd-division/country:us/state:mo"}, "scraped_at": "2025-07-28T19:17:47+00:00", "_id": "8bcc05a8-6be7-11f0-b2b7-9a04959f051b"}