{"identifier": "", "motion_text": "Reported Do Pass (H) - AYES: 9 NOES: 0 PRESENT: 4", "motion_classification": ["passage"], "start_date": "2025-04-24T05:00:00+00:00", "result": "pass", "organization": "~{\"classification\": \"lower\"}", "legislative_session": "2025", "bill": "e722a976-6be6-11f0-b2b7-9a04959f051b", "bill_action": null, "bill_identifier": "HB 1349", "votes": [], "counts": [], "sources": [{"url": "https://house.mo.gov/billactions.aspx?bill=HB1349&year=2025&code=R", "note": ""}], "extras": {}, "_id": "e722d252-6be6-11f0-b2b7-9a04959f051b"}