{"identifier": "", "motion_text": "Reported Do Pass (H) - AYES: 13 NOES: 1 PRESENT: 0", "motion_classification": ["passage"], "start_date": "2025-04-24T05:00:00+00:00", "result": "pass", "organization": "~{\"classification\": \"lower\"}", "legislative_session": "2025", "bill": "ec487a14-6bf2-11f0-a189-ea4745df1a12", "bill_action": null, "bill_identifier": "HB 1572", "votes": [], "counts": [], "sources": [{"url": "https://house.mo.gov/billactions.aspx?bill=HB1572&year=2025&code=R", "note": ""}], "extras": {}, "_id": "ec48a020-6bf2-11f0-a189-ea4745df1a12"}