{"identifier": "", "motion_text": "Third Read and Passed (H) - AYES: 155 NOES: 0 PRESENT: 0", "motion_classification": ["passage"], "start_date": "2025-04-07T05:00:00+00:00", "result": "pass", "organization": "~{\"classification\": \"lower\"}", "legislative_session": "2025", "bill": "3420a7c4-6be6-11f0-b2b7-9a04959f051b", "bill_action": null, "bill_identifier": "HB 1049", "votes": [], "counts": [], "sources": [{"url": "https://house.mo.gov/billactions.aspx?bill=HB1049&year=2025&code=R", "note": ""}], "extras": {}, "_id": "342102fa-6be6-11f0-b2b7-9a04959f051b"}